integration_test/__about__.py
integration_test/__init__.py
integration_test-0.0.2.dist-info/METADATA
integration_test-0.0.2.dist-info/WHEEL
integration_test-0.0.2.dist-info/licenses/LICENSE.txt
integration_test-0.0.2.dist-info/RECORD
