Metadata-Version: 2.1
Name: integration-test
Version: 0.0.2
Summary: Collection of automated test cases
Project-URL: Documentation, https://gitlab.iavgroup.local/In-CarApps/test-automation/oru/integration_test#readme
Project-URL: Issues, https://gitlab.iavgroup.local/In-CarApps/test-automation/oru/integration_test/issues
Project-URL: Source, https://gitlab.iavgroup.local/In-CarApps/test-automation/oru/integration-test
Author-email: Sven Siegmund <sven.siegmund@iav.de>
License-File: LICENSE.txt
Classifier: Development Status :: 4 - Beta
Classifier: Programming Language :: Python
Classifier: Programming Language :: Python :: 3.10
Classifier: Programming Language :: Python :: Implementation :: CPython
Classifier: Programming Language :: Python :: Implementation :: PyPy
Requires-Python: >=3.10
Requires-Dist: tamarisk
Requires-Dist: wattle
